cutthecrab/__init__.py
cutthecrab-0.1.0.dist-info/LICENSE
cutthecrab-0.1.0.dist-info/METADATA
cutthecrab-0.1.0.dist-info/WHEEL
cutthecrab-0.1.0.dist-info/top_level.txt
cutthecrab-0.1.0.dist-info/RECORD
